{
  "build": "h90c84d6_0",
  "build_number": 0,
  "channel": "https://repo.anaconda.com/pkgs/main/win-64",
  "constrains": [],
  "depends": [
    "libhwloc >=2.12.1,<2.12.2.0a0",
    "ucrt >=10.0.20348.0",
    "vc >=14.2,<15",
    "vc14_runtime >=14.29.30133"
  ],
  "extracted_package_dir": "C:\\Users\\32838\\.conda\\pkgs\\tbb-2022.3.0-h90c84d6_0",
  "files": [
    "Library/bin/tbb12.dll",
    "Library/bin/tbbbind_2_5.dll",
    "Library/bin/tbbmalloc.dll",
    "Library/bin/tbbmalloc_proxy.dll"
  ],
  "fn": "tbb-2022.3.0-h90c84d6_0.conda",
  "legacy_bz2_md5": "386ac0fdc3bf21317e03762cf90695c2",
  "license": "Apache-2.0",
  "license_family": "Apache",
  "link": {
    "source": "C:\\Users\\32838\\.conda\\pkgs\\tbb-2022.3.0-h90c84d6_0",
    "type": 1
  },
  "md5": "2bf446510a51e17350dcd40a99d1333f",
  "name": "tbb",
  "package_tarball_full_path": "C:\\Users\\32838\\.conda\\pkgs\\tbb-2022.3.0-h90c84d6_0.conda",
  "paths_data": {
    "paths": [
      {
        "_path": "Library/bin/tbb12.dll",
        "path_type": "hardlink",
        "sha256": "b961bd3d24cc35c2ee6940ce94f9a1e09aa8a2bfe9c7a6cd972b1badc2c17995",
        "sha256_in_prefix": "b961bd3d24cc35c2ee6940ce94f9a1e09aa8a2bfe9c7a6cd972b1badc2c17995",
        "size_in_bytes": 351048
      },
      {
        "_path": "Library/bin/tbbbind_2_5.dll",
        "path_type": "hardlink",
        "sha256": "b52e1ccc2b2d3ed9cbd6d202e8046618598629da224d2b1d9d081caf80115d74",
        "sha256_in_prefix": "b52e1ccc2b2d3ed9cbd6d202e8046618598629da224d2b1d9d081caf80115d74",
        "size_in_bytes": 36680
      },
      {
        "_path": "Library/bin/tbbmalloc.dll",
        "path_type": "hardlink",
        "sha256": "595689cd9be77fff067bd0df1f3d44d1090846be346ea337efd40738637d441e",
        "sha256_in_prefix": "595689cd9be77fff067bd0df1f3d44d1090846be346ea337efd40738637d441e",
        "size_in_bytes": 124744
      },
      {
        "_path": "Library/bin/tbbmalloc_proxy.dll",
        "path_type": "hardlink",
        "sha256": "9cb62a4442ad383cf8b40cd6dc22f718a6f6d7e996ac1af52b95f1d559b5e8be",
        "sha256_in_prefix": "9cb62a4442ad383cf8b40cd6dc22f718a6f6d7e996ac1af52b95f1d559b5e8be",
        "size_in_bytes": 43336
      }
    ],
    "paths_version": 1
  },
  "requested_spec": "None",
  "sha256": "40cd6dad655407ba9fc1cf56e7504a5a5865427f703b0f7ebdf4718cf3975b66",
  "size": 165498,
  "subdir": "win-64",
  "timestamp": 1764336927072,
  "url": "https://repo.anaconda.com/pkgs/main/win-64/tbb-2022.3.0-h90c84d6_0.conda",
  "version": "2022.3.0"
}